{
  "db_name": "PostgreSQL",
  "query": "\n            UPDATE corporations\n            SET\n                uuid = $1,\n                session_uuid = $2,\n                user_uuid = $3,\n                name = $4,\n                balance = $5\n            WHERE uuid = $1\n            RETURNING uuid, session_uuid, user_uuid, name, balance\n            ",
  "describe": {
    "columns": [
      {
        "ordinal": 0,
        "name": "uuid",
        "type_info": "Uuid"
      },
      {
        "ordinal": 1,
        "name": "session_uuid",
        "type_info": "Uuid"
      },
      {
        "ordinal": 2,
        "name": "user_uuid",
        "type_info": "Uuid"
      },
      {
        "ordinal": 3,
        "name": "name",
        "type_info": "Text"
      },
      {
        "ordinal": 4,
        "name": "balance",
        "type_info": "Int8"
      }
    ],
    "parameters": {
      "Left": [
        "Uuid",
        "Uuid",
        "Uuid",
        "Text",
        "Int8"
      ]
    },
    "nullable": [
      false,
      false,
      false,
      false,
      false
    ]
  },
  "hash": "0de7bcea0028df519b20b62571a08d37090d4fc8bfa142af4e68724f46c7b7b9"
}
